{
    "appVersion": "1.0",
    "generatedAt": "2026-01-26 16:27:37",
    "files": [
        {
            "path": "sa_state.json",
            "size": 70,
            "md5": "c13c51fbd6d73ca5014c4bc53ca61a44"
        },
        {
            "path": "Data/Blocks.json",
            "size": 496,
            "md5": "205e9b784e799ce2e49006da89e872e5"
        },
        {
            "path": "Data/config.JSON",
            "size": 54,
            "md5": "56479160046a4c6437af4aee4be82ad5"
        },
        {
            "path": "Data/Items.json",
            "size": 16317,
            "md5": "06d1eee444c5ef5df26a82216cd40efa"
        },
        {
            "path": "Data/Players.json",
            "size": 242,
            "md5": "cc08a8463a5521458a4db8873313b254"
        },
        {
            "path": "Data/Stages.json",
            "size": 1106,
            "md5": "e94742b9e10076c41d614bba82dbd21b"
        },
        {
            "path": "Data/Upgrades.json",
            "size": 7984,
            "md5": "9ca70c47bade0a41455c79a65e14b965"
        }
    ]
}